COPYING
README
ez_setup.py
memento.py
setup.py
memento.egg-info/PKG-INFO
memento.egg-info/SOURCES.txt
memento.egg-info/dependency_links.txt
memento.egg-info/requires.txt
memento.egg-info/top_level.txt
